rpi_ky_040/__init__.py
rpi_ky_040/_ky_040.py
rpi_ky_040-0.1.0.dist-info/WHEEL
rpi_ky_040-0.1.0.dist-info/METADATA
rpi_ky_040-0.1.0.dist-info/RECORD
